cached_historical_data_fetcher/__init__.py
cached_historical_data_fetcher/cache/__init__.py
cached_historical_data_fetcher/cache/base.py
cached_historical_data_fetcher/cache/chunk.py
cached_historical_data_fetcher/cache/id.py
cached_historical_data_fetcher/io.py
cached_historical_data_fetcher/py.typed
cached_historical_data_fetcher-0.2.31.dist-info/LICENSE
cached_historical_data_fetcher-0.2.31.dist-info/METADATA
cached_historical_data_fetcher-0.2.31.dist-info/WHEEL
cached_historical_data_fetcher-0.2.31.dist-info/RECORD
