Metadata-Version: 2.3
Name: cached-historical-data-fetcher
Version: 0.2.31
Summary: Python utility for fetching any historical data using caching.
License: MIT
Author: 34j
Author-email: 34j.95a2p@simplelogin.com
Requires-Python: >=3.9,<3.13
Classifier: Development Status :: 2 - Pre-Alpha
Classifier: Intended Audience :: Developers
Classifier: License :: OSI Approved :: MIT License
Classifier: Natural Language :: English
Classifier: Operating System :: OS Independent
Classifier: Programming Language :: Python :: 3
Classifier: Programming Language :: Python :: 3.9
Classifier: Programming Language :: Python :: 3.10
Classifier: Programming Language :: Python :: 3.11
Classifier: Programming Language :: Python :: 3.12
Classifier: Topic :: Software Development :: Libraries
Requires-Dist: aiofiles (>=23.2.1,<24.0.0)
Requires-Dist: joblib (>=1.3.2,<2.0.0)
Requires-Dist: lz4 (>=4.3.2,<5.0.0)
Requires-Dist: numpy (>=1.26.0,<2.0.0)
Requires-Dist: pandas (>=2.1.1,<3.0.0)
Requires-Dist: python-slugify (>=8.0.1,<9.0.0)
Requires-Dist: tqdm (>=4.66.1,<5.0.0)
Requires-Dist: typing-extensions (>=4.8.0,<5.0.0)
Project-URL: Bug Tracker, https://github.com/34j/cached-historical-data-fetcher/issues
Project-URL: Changelog, https://github.com/34j/cached-historical-data-fetcher/blob/main/CHANGELOG.md
Project-URL: Documentation, https://cached-historical-data-fetcher.readthedocs.io
Project-URL: Repository, https://github.com/34j/cached-historical-data-fetcher
